fuso/__init__.py
fuso/dotpath.py
fuso/merge.py
fuso/utils.py
fuso-0.1.5.dist-info/WHEEL
fuso-0.1.5.dist-info/METADATA
fuso-0.1.5.dist-info/RECORD
