Metadata-Version: 2.3
Name: fuso
Version: 0.1.5
Summary: Add your description here
Author: Jens Peder Meldgaard
Author-email: Jens Peder Meldgaard <jenspederm@gmail.com>
Requires-Python: >=3.11
Project-URL: Homepage, https://github.com/jenspederm/fuso
Project-URL: Issues, https://github.com/jenspederm/fuso/issues
